_atoti_server/__init__.py
_atoti_server/__resources__/application.jar
_atoti_server/__resources__/atoti-admin-ui.jar
_atoti_server/__resources__/atoti-ui-initial-content.jar
_atoti_server/__resources__/community.lic
_atoti_server/__resources__/hadoop-3.2.1/bin/hadoop.dll
_atoti_server/__resources__/hadoop-3.2.1/bin/winutils.exe
_atoti_server/__resources__/server.jar
_atoti_server/_add_opens.py
_atoti_server/_copy_output.py
_atoti_server/_create_flight_recording.py
_atoti_server/_get_java_executable_path.py
_atoti_server/_resources_directory.py
_atoti_server/_supported_java_version.py
_atoti_server/_wait_for_matching_output.py
_atoti_server/py.typed
_atoti_server/resolve_license_key.py
_atoti_server/retrieve_spring_application_port.py
_atoti_server/server_subprocess.py
atoti_server-0.9.12.dist-info/WHEEL
atoti_server-0.9.12.dist-info/METADATA
atoti_server-0.9.12.dist-info/RECORD
