Metadata-Version: 2.3
Name: atoti-server
Version: 0.9.12
Summary: Resources to start a new Atoti session
Author: ActiveViam
Author-email: ActiveViam <atoti-dev@activeviam.com>
Classifier: Development Status :: 4 - Beta
Classifier: License :: Free for non-commercial use
Classifier: Operating System :: OS Independent
Classifier: Programming Language :: Java
Classifier: Programming Language :: Python :: 3
Classifier: Typing :: Typed
Requires-Dist: atoti-core==0.9.12
Requires-Dist: atoti-server-aws==0.9.12 ; extra == 'aws'
Requires-Dist: atoti-server-azure==0.9.12 ; extra == 'azure'
Requires-Dist: atoti-server-directquery-bigquery==0.9.12 ; extra == 'directquery-bigquery'
Requires-Dist: atoti-server-directquery-clickhouse==0.9.12 ; extra == 'directquery-clickhouse'
Requires-Dist: atoti-server-directquery-databricks==0.9.12 ; extra == 'directquery-databricks'
Requires-Dist: atoti-server-directquery-jdbc==0.9.12 ; extra == 'directquery-jdbc'
Requires-Dist: atoti-server-directquery-mssql==0.9.12 ; extra == 'directquery-mssql'
Requires-Dist: atoti-server-directquery-redshift==0.9.12 ; extra == 'directquery-redshift'
Requires-Dist: atoti-server-directquery-snowflake==0.9.12 ; extra == 'directquery-snowflake'
Requires-Dist: atoti-server-directquery-synapse==0.9.12 ; extra == 'directquery-synapse'
Requires-Dist: atoti-server-gcp==0.9.12 ; extra == 'gcp'
Requires-Dist: atoti-server-jdbc==0.9.12 ; extra == 'jdbc'
Requires-Dist: atoti-jupyterlab==0.9.12 ; extra == 'jupyterlab'
Requires-Dist: atoti-server-kafka==0.9.12 ; extra == 'kafka'
Requires-Dist: atoti-server-observability==0.9.12 ; extra == 'observability'
Requires-Dist: atoti-server-parquet==0.9.12 ; extra == 'parquet'
Requires-Dist: atoti-server-spring-boot-admin==0.9.12 ; extra == 'spring-boot-admin'
Requires-Dist: atoti-server-sql-bridge==0.9.12 ; extra == 'sql-bridge'
Requires-Python: >=3.10
Project-URL: Homepage, https://www.atoti.io
Project-URL: Issues, https://github.com/atoti/atoti/issues
Provides-Extra: aws
Provides-Extra: azure
Provides-Extra: directquery-bigquery
Provides-Extra: directquery-clickhouse
Provides-Extra: directquery-databricks
Provides-Extra: directquery-jdbc
Provides-Extra: directquery-mssql
Provides-Extra: directquery-redshift
Provides-Extra: directquery-snowflake
Provides-Extra: directquery-synapse
Provides-Extra: gcp
Provides-Extra: jdbc
Provides-Extra: jupyterlab
Provides-Extra: kafka
Provides-Extra: observability
Provides-Extra: parquet
Provides-Extra: spring-boot-admin
Provides-Extra: sql-bridge
